README.rst
setup.py
django_query_logger.egg-info/PKG-INFO
django_query_logger.egg-info/SOURCES.txt
django_query_logger.egg-info/dependency_links.txt
django_query_logger.egg-info/pbr.json
django_query_logger.egg-info/requires.txt
django_query_logger.egg-info/top_level.txt
query_logger/__init__.py
query_logger/config.py
query_logger/mixin.py